mongoflow/__init__.py
mongoflow/async_connection.py
mongoflow/async_model.py
mongoflow/async_query_builder.py
mongoflow/async_repository.py
mongoflow/base.py
mongoflow/connection.py
mongoflow/decorators.py
mongoflow/exceptions.py
mongoflow/fields.py
mongoflow/model.py
mongoflow/query_builder.py
mongoflow/repository.py
mongoflow/types.py
mongoflow/utils.py
mongoflow/version.py
mongoflow/mixins/__init__.py
mongoflow/mixins/cacheable.py
mongoflow/mixins/searchable.py
mongoflow/mixins/soft_delete.py
mongoflow/mixins/timestampable.py
mongoflow/mixins/versionable.py
mongoflow-0.1.0.dist-info/licenses/LICENSE
mongoflow-0.1.0.dist-info/METADATA
mongoflow-0.1.0.dist-info/WHEEL
mongoflow-0.1.0.dist-info/top_level.txt
mongoflow-0.1.0.dist-info/RECORD
